{"@t":"2019-10-21T08:19:51.2325080Z","@mt":"{StartMessage} [Timing {TimingId}]","StartMessage":"Booting Umbraco 8.1.5.","TimingId":"e083300","SourceContext":"Umbraco.Core.Runtime.CoreRuntime","ProcessId":9500,"ProcessName":"iisexpress","ThreadId":1,"AppDomainId":2,"AppDomainAppId":"LMW3SVC2ROOT","MachineName":"LAPTOP-7D4JH2DL","Log4NetLevel":"INFO ","HttpRequestNumber":1,"HttpRequestId":"bef2b4da-4463-42a0-b09a-3f970e5a8f48"}
{"@t":"2019-10-21T08:19:51.2700912Z","@mt":"Booting site '{HostingSiteName}', app '{HostingApplicationID}', path '{HostingPhysicalPath}', server '{MachineName}'.","HostingSiteName":"gnollhack2","HostingApplicationID":"/LM/W3SVC/2/ROOT","HostingPhysicalPath":"C:\\Users\\tanel\\source\\repos\\gnollhack-website3\\gnollhack-website\\gnollhack2\\","MachineName":"LAPTOP-7D4JH2DL","SourceContext":"Umbraco.Core.Runtime.CoreRuntime","ProcessId":9500,"ProcessName":"iisexpress","ThreadId":1,"AppDomainId":2,"AppDomainAppId":"LMW3SVC2ROOT","Log4NetLevel":"INFO ","HttpRequestNumber":1,"HttpRequestId":"bef2b4da-4463-42a0-b09a-3f970e5a8f48"}
{"@t":"2019-10-21T08:19:51.6234567Z","@mt":"Acquiring.","SourceContext":"Umbraco.Core.MainDom","ProcessId":9500,"ProcessName":"iisexpress","ThreadId":1,"AppDomainId":2,"AppDomainAppId":"LMW3SVC2ROOT","MachineName":"LAPTOP-7D4JH2DL","Log4NetLevel":"INFO ","HttpRequestNumber":1,"HttpRequestId":"bef2b4da-4463-42a0-b09a-3f970e5a8f48"}
{"@t":"2019-10-21T08:19:51.6433819Z","@mt":"Acquired.","SourceContext":"Umbraco.Core.MainDom","ProcessId":9500,"ProcessName":"iisexpress","ThreadId":1,"AppDomainId":2,"AppDomainAppId":"LMW3SVC2ROOT","MachineName":"LAPTOP-7D4JH2DL","Log4NetLevel":"INFO ","HttpRequestNumber":1,"HttpRequestId":"bef2b4da-4463-42a0-b09a-3f970e5a8f48"}
{"@t":"2019-10-21T08:19:53.9306947Z","@mt":"{StartMessage} [Timing {TimingId}]","StartMessage":"Resolving composer types.","TimingId":"4f36702","SourceContext":"Umbraco.Core.Runtime.CoreRuntime","ProcessId":9500,"ProcessName":"iisexpress","ThreadId":1,"AppDomainId":2,"AppDomainAppId":"LMW3SVC2ROOT","MachineName":"LAPTOP-7D4JH2DL","Log4NetLevel":"INFO ","HttpRequestNumber":1,"HttpRequestId":"bef2b4da-4463-42a0-b09a-3f970e5a8f48"}
{"@t":"2019-10-21T08:19:54.5665245Z","@mt":"{EndMessage} ({Duration}ms) [Timing {TimingId}]","EndMessage":"Resolved.","Duration":637,"TimingId":"4f36702","SourceContext":"Umbraco.Core.Runtime.CoreRuntime","ProcessId":9500,"ProcessName":"iisexpress","ThreadId":1,"AppDomainId":2,"AppDomainAppId":"LMW3SVC2ROOT","MachineName":"LAPTOP-7D4JH2DL","Log4NetLevel":"INFO ","HttpRequestNumber":1,"HttpRequestId":"bef2b4da-4463-42a0-b09a-3f970e5a8f48"}
{"@t":"2019-10-21T08:19:58.2973990Z","@mt":"The culture specified {Culture} was not found in any configured sources for this service","@l":"Warning","Culture":"fi-FI","SourceContext":"Umbraco.Core.Services.Implement.LocalizedTextService","ProcessId":9500,"ProcessName":"iisexpress","ThreadId":1,"AppDomainId":2,"AppDomainAppId":"LMW3SVC2ROOT","MachineName":"LAPTOP-7D4JH2DL","Log4NetLevel":"WARN ","HttpRequestNumber":1,"HttpRequestId":"bef2b4da-4463-42a0-b09a-3f970e5a8f48"}
{"@t":"2019-10-21T08:19:58.2973990Z","@mt":"The culture specified {Culture} was not found in any configured sources for this service","@l":"Warning","Culture":"fi-FI","SourceContext":"Umbraco.Core.Services.Implement.LocalizedTextService","ProcessId":9500,"ProcessName":"iisexpress","ThreadId":1,"AppDomainId":2,"AppDomainAppId":"LMW3SVC2ROOT","MachineName":"LAPTOP-7D4JH2DL","Log4NetLevel":"WARN ","HttpRequestNumber":1,"HttpRequestId":"bef2b4da-4463-42a0-b09a-3f970e5a8f48"}
{"@t":"2019-10-21T08:19:58.2973990Z","@mt":"The culture specified {Culture} was not found in any configured sources for this service","@l":"Warning","Culture":"fi-FI","SourceContext":"Umbraco.Core.Services.Implement.LocalizedTextService","ProcessId":9500,"ProcessName":"iisexpress","ThreadId":1,"AppDomainId":2,"AppDomainAppId":"LMW3SVC2ROOT","MachineName":"LAPTOP-7D4JH2DL","Log4NetLevel":"WARN ","HttpRequestNumber":1,"HttpRequestId":"bef2b4da-4463-42a0-b09a-3f970e5a8f48"}
{"@t":"2019-10-21T08:19:58.3016508Z","@mt":"The culture specified {Culture} was not found in any configured sources for this service","@l":"Warning","Culture":"fi-FI","SourceContext":"Umbraco.Core.Services.Implement.LocalizedTextService","ProcessId":9500,"ProcessName":"iisexpress","ThreadId":1,"AppDomainId":2,"AppDomainAppId":"LMW3SVC2ROOT","MachineName":"LAPTOP-7D4JH2DL","Log4NetLevel":"WARN ","HttpRequestNumber":1,"HttpRequestId":"bef2b4da-4463-42a0-b09a-3f970e5a8f48"}
{"@t":"2019-10-21T08:19:58.3026475Z","@mt":"The culture specified {Culture} was not found in any configured sources for this service","@l":"Warning","Culture":"fi-FI","SourceContext":"Umbraco.Core.Services.Implement.LocalizedTextService","ProcessId":9500,"ProcessName":"iisexpress","ThreadId":1,"AppDomainId":2,"AppDomainAppId":"LMW3SVC2ROOT","MachineName":"LAPTOP-7D4JH2DL","Log4NetLevel":"WARN ","HttpRequestNumber":1,"HttpRequestId":"bef2b4da-4463-42a0-b09a-3f970e5a8f48"}
{"@t":"2019-10-21T08:19:58.3026475Z","@mt":"The culture specified {Culture} was not found in any configured sources for this service","@l":"Warning","Culture":"fi-FI","SourceContext":"Umbraco.Core.Services.Implement.LocalizedTextService","ProcessId":9500,"ProcessName":"iisexpress","ThreadId":1,"AppDomainId":2,"AppDomainAppId":"LMW3SVC2ROOT","MachineName":"LAPTOP-7D4JH2DL","Log4NetLevel":"WARN ","HttpRequestNumber":1,"HttpRequestId":"bef2b4da-4463-42a0-b09a-3f970e5a8f48"}
{"@t":"2019-10-21T08:19:58.3026475Z","@mt":"The culture specified {Culture} was not found in any configured sources for this service","@l":"Warning","Culture":"fi-FI","SourceContext":"Umbraco.Core.Services.Implement.LocalizedTextService","ProcessId":9500,"ProcessName":"iisexpress","ThreadId":1,"AppDomainId":2,"AppDomainAppId":"LMW3SVC2ROOT","MachineName":"LAPTOP-7D4JH2DL","Log4NetLevel":"WARN ","HttpRequestNumber":1,"HttpRequestId":"bef2b4da-4463-42a0-b09a-3f970e5a8f48"}
{"@t":"2019-10-21T08:19:58.3043815Z","@mt":"The culture specified {Culture} was not found in any configured sources for this service","@l":"Warning","Culture":"fi-FI","SourceContext":"Umbraco.Core.Services.Implement.LocalizedTextService","ProcessId":9500,"ProcessName":"iisexpress","ThreadId":1,"AppDomainId":2,"AppDomainAppId":"LMW3SVC2ROOT","MachineName":"LAPTOP-7D4JH2DL","Log4NetLevel":"WARN ","HttpRequestNumber":1,"HttpRequestId":"bef2b4da-4463-42a0-b09a-3f970e5a8f48"}
{"@t":"2019-10-21T08:19:58.3588464Z","@mt":"The culture specified {Culture} was not found in any configured sources for this service","@l":"Warning","Culture":"fi-FI","SourceContext":"Umbraco.Core.Services.Implement.LocalizedTextService","ProcessId":9500,"ProcessName":"iisexpress","ThreadId":1,"AppDomainId":2,"AppDomainAppId":"LMW3SVC2ROOT","MachineName":"LAPTOP-7D4JH2DL","Log4NetLevel":"WARN ","HttpRequestNumber":1,"HttpRequestId":"bef2b4da-4463-42a0-b09a-3f970e5a8f48"}
{"@t":"2019-10-21T08:19:58.3598440Z","@mt":"The culture specified {Culture} was not found in any configured sources for this service","@l":"Warning","Culture":"fi-FI","SourceContext":"Umbraco.Core.Services.Implement.LocalizedTextService","ProcessId":9500,"ProcessName":"iisexpress","ThreadId":1,"AppDomainId":2,"AppDomainAppId":"LMW3SVC2ROOT","MachineName":"LAPTOP-7D4JH2DL","Log4NetLevel":"WARN ","HttpRequestNumber":1,"HttpRequestId":"bef2b4da-4463-42a0-b09a-3f970e5a8f48"}
{"@t":"2019-10-21T08:20:04.5290790Z","@mt":"Profiler is VoidProfiler, not profiling (must run debug mode to profile).","SourceContext":"Umbraco.Web.Logging.WebProfilerComponent","ProcessId":9500,"ProcessName":"iisexpress","ThreadId":1,"AppDomainId":2,"AppDomainAppId":"LMW3SVC2ROOT","MachineName":"LAPTOP-7D4JH2DL","Log4NetLevel":"INFO ","HttpRequestNumber":1,"HttpRequestId":"bef2b4da-4463-42a0-b09a-3f970e5a8f48"}
{"@t":"2019-10-21T08:20:04.9510501Z","@mt":"Initializing Umbraco internal event handlers for cache refreshing.","SourceContext":"Umbraco.Web.Cache.DistributedCacheBinderComponent","ProcessId":9500,"ProcessName":"iisexpress","ThreadId":1,"AppDomainId":2,"AppDomainAppId":"LMW3SVC2ROOT","MachineName":"LAPTOP-7D4JH2DL","Log4NetLevel":"INFO ","HttpRequestNumber":1,"HttpRequestId":"bef2b4da-4463-42a0-b09a-3f970e5a8f48"}
{"@t":"2019-10-21T08:20:05.2067908Z","@mt":"Adding examine event handlers for {RegisteredIndexers} index providers.","RegisteredIndexers":3,"SourceContext":"Umbraco.Web.Search.ExamineComponent","ProcessId":9500,"ProcessName":"iisexpress","ThreadId":1,"AppDomainId":2,"AppDomainAppId":"LMW3SVC2ROOT","MachineName":"LAPTOP-7D4JH2DL","Log4NetLevel":"INFO ","HttpRequestNumber":1,"HttpRequestId":"bef2b4da-4463-42a0-b09a-3f970e5a8f48"}
{"@t":"2019-10-21T08:20:05.6598026Z","@mt":"Starting initialize async background thread.","SourceContext":"Umbraco.Web.Search.BackgroundIndexRebuilder","ProcessId":9500,"ProcessName":"iisexpress","ThreadId":1,"AppDomainId":2,"AppDomainAppId":"LMW3SVC2ROOT","MachineName":"LAPTOP-7D4JH2DL","Log4NetLevel":"INFO ","HttpRequestNumber":1,"HttpRequestId":"bef2b4da-4463-42a0-b09a-3f970e5a8f48"}
{"@t":"2019-10-21T08:20:05.6990438Z","@mt":"{EndMessage} ({Duration}ms) [Timing {TimingId}]","EndMessage":"Booted.","Duration":14485,"TimingId":"e083300","SourceContext":"Umbraco.Core.Runtime.CoreRuntime","ProcessId":9500,"ProcessName":"iisexpress","ThreadId":1,"AppDomainId":2,"AppDomainAppId":"LMW3SVC2ROOT","MachineName":"LAPTOP-7D4JH2DL","Log4NetLevel":"INFO ","HttpRequestNumber":1,"HttpRequestId":"bef2b4da-4463-42a0-b09a-3f970e5a8f48"}
{"@t":"2019-10-21T08:20:06.7586541Z","@mt":"New url {Url} detected, re-discovering application url.","Url":"http://localhost:58600/umbraco","SourceContext":"Umbraco.Core.Sync.ApplicationUrlHelper","ProcessId":9500,"ProcessName":"iisexpress","ThreadId":11,"AppDomainId":2,"AppDomainAppId":"LMW3SVC2ROOT","MachineName":"LAPTOP-7D4JH2DL","Log4NetLevel":"INFO ","HttpRequestNumber":2,"HttpRequestId":"732c7f59-10ec-4f98-9343-872b06a355c7"}
{"@t":"2019-10-21T08:20:06.7586541Z","@mt":"New url {Url} detected, re-discovering application url.","Url":"http://localhost:58600/umbraco","SourceContext":"Umbraco.Core.Sync.ApplicationUrlHelper","ProcessId":9500,"ProcessName":"iisexpress","ThreadId":8,"AppDomainId":2,"AppDomainAppId":"LMW3SVC2ROOT","MachineName":"LAPTOP-7D4JH2DL","Log4NetLevel":"INFO ","HttpRequestNumber":3,"HttpRequestId":"372a7b2c-e40d-4813-b1fd-d482f9aad1f7"}
{"@t":"2019-10-21T08:20:06.7586541Z","@mt":"ApplicationUrl: {UmbracoAppUrl} (UmbracoModule request)","UmbracoAppUrl":"http://localhost:58600/umbraco","SourceContext":"Umbraco.Core.Sync.ApplicationUrlHelper","ProcessId":9500,"ProcessName":"iisexpress","ThreadId":11,"AppDomainId":2,"AppDomainAppId":"LMW3SVC2ROOT","MachineName":"LAPTOP-7D4JH2DL","Log4NetLevel":"INFO ","HttpRequestNumber":2,"HttpRequestId":"732c7f59-10ec-4f98-9343-872b06a355c7"}
{"@t":"2019-10-21T08:20:06.7586541Z","@mt":"ApplicationUrl: {UmbracoAppUrl} (UmbracoModule request)","UmbracoAppUrl":"http://localhost:58600/umbraco","SourceContext":"Umbraco.Core.Sync.ApplicationUrlHelper","ProcessId":9500,"ProcessName":"iisexpress","ThreadId":8,"AppDomainId":2,"AppDomainAppId":"LMW3SVC2ROOT","MachineName":"LAPTOP-7D4JH2DL","Log4NetLevel":"INFO ","HttpRequestNumber":3,"HttpRequestId":"372a7b2c-e40d-4813-b1fd-d482f9aad1f7"}
{"@t":"2019-10-21T08:21:07.9249692Z","@mt":"The culture specified {Culture} was not found in any configured sources for this service","@l":"Warning","Culture":"fi-FI","SourceContext":"Umbraco.Core.Services.Implement.LocalizedTextService","ProcessId":9500,"ProcessName":"iisexpress","ThreadId":11,"AppDomainId":2,"AppDomainAppId":"LMW3SVC2ROOT","MachineName":"LAPTOP-7D4JH2DL","Log4NetLevel":"WARN "}
{"@t":"2019-10-21T08:21:07.9268663Z","@mt":"The culture specified {Culture} was not found in any configured sources for this service","@l":"Warning","Culture":"fi-FI","SourceContext":"Umbraco.Core.Services.Implement.LocalizedTextService","ProcessId":9500,"ProcessName":"iisexpress","ThreadId":11,"AppDomainId":2,"AppDomainAppId":"LMW3SVC2ROOT","MachineName":"LAPTOP-7D4JH2DL","Log4NetLevel":"WARN "}
{"@t":"2019-10-21T08:21:07.9608031Z","@mt":"The culture specified {Culture} was not found in any configured sources for this service","@l":"Warning","Culture":"fi-FI","SourceContext":"Umbraco.Core.Services.Implement.LocalizedTextService","ProcessId":9500,"ProcessName":"iisexpress","ThreadId":11,"AppDomainId":2,"AppDomainAppId":"LMW3SVC2ROOT","MachineName":"LAPTOP-7D4JH2DL","Log4NetLevel":"WARN "}
{"@t":"2019-10-21T08:21:07.9916852Z","@mt":"The culture specified {Culture} was not found in any configured sources for this service","@l":"Warning","Culture":"fi-FI","SourceContext":"Umbraco.Core.Services.Implement.LocalizedTextService","ProcessId":9500,"ProcessName":"iisexpress","ThreadId":11,"AppDomainId":2,"AppDomainAppId":"LMW3SVC2ROOT","MachineName":"LAPTOP-7D4JH2DL","Log4NetLevel":"WARN "}
{"@t":"2019-10-21T08:21:08.0590772Z","@mt":"The culture specified {Culture} was not found in any configured sources for this service","@l":"Warning","Culture":"fi-FI","SourceContext":"Umbraco.Core.Services.Implement.LocalizedTextService","ProcessId":9500,"ProcessName":"iisexpress","ThreadId":11,"AppDomainId":2,"AppDomainAppId":"LMW3SVC2ROOT","MachineName":"LAPTOP-7D4JH2DL","Log4NetLevel":"WARN "}
{"@t":"2019-10-21T08:21:08.0590772Z","@mt":"The culture specified {Culture} was not found in any configured sources for this service","@l":"Warning","Culture":"fi-FI","SourceContext":"Umbraco.Core.Services.Implement.LocalizedTextService","ProcessId":9500,"ProcessName":"iisexpress","ThreadId":11,"AppDomainId":2,"AppDomainAppId":"LMW3SVC2ROOT","MachineName":"LAPTOP-7D4JH2DL","Log4NetLevel":"WARN "}
{"@t":"2019-10-21T08:21:08.0604963Z","@mt":"The culture specified {Culture} was not found in any configured sources for this service","@l":"Warning","Culture":"fi-FI","SourceContext":"Umbraco.Core.Services.Implement.LocalizedTextService","ProcessId":9500,"ProcessName":"iisexpress","ThreadId":11,"AppDomainId":2,"AppDomainAppId":"LMW3SVC2ROOT","MachineName":"LAPTOP-7D4JH2DL","Log4NetLevel":"WARN "}
{"@t":"2019-10-21T08:21:08.0604963Z","@mt":"The culture specified {Culture} was not found in any configured sources for this service","@l":"Warning","Culture":"fi-FI","SourceContext":"Umbraco.Core.Services.Implement.LocalizedTextService","ProcessId":9500,"ProcessName":"iisexpress","ThreadId":11,"AppDomainId":2,"AppDomainAppId":"LMW3SVC2ROOT","MachineName":"LAPTOP-7D4JH2DL","Log4NetLevel":"WARN "}
{"@t":"2019-10-21T08:21:08.0614934Z","@mt":"The culture specified {Culture} was not found in any configured sources for this service","@l":"Warning","Culture":"fi-FI","SourceContext":"Umbraco.Core.Services.Implement.LocalizedTextService","ProcessId":9500,"ProcessName":"iisexpress","ThreadId":11,"AppDomainId":2,"AppDomainAppId":"LMW3SVC2ROOT","MachineName":"LAPTOP-7D4JH2DL","Log4NetLevel":"WARN "}
{"@t":"2019-10-21T08:21:08.0614934Z","@mt":"The culture specified {Culture} was not found in any configured sources for this service","@l":"Warning","Culture":"fi-FI","SourceContext":"Umbraco.Core.Services.Implement.LocalizedTextService","ProcessId":9500,"ProcessName":"iisexpress","ThreadId":11,"AppDomainId":2,"AppDomainAppId":"LMW3SVC2ROOT","MachineName":"LAPTOP-7D4JH2DL","Log4NetLevel":"WARN "}
{"@t":"2019-10-21T08:21:08.0614934Z","@mt":"The culture specified {Culture} was not found in any configured sources for this service","@l":"Warning","Culture":"fi-FI","SourceContext":"Umbraco.Core.Services.Implement.LocalizedTextService","ProcessId":9500,"ProcessName":"iisexpress","ThreadId":11,"AppDomainId":2,"AppDomainAppId":"LMW3SVC2ROOT","MachineName":"LAPTOP-7D4JH2DL","Log4NetLevel":"WARN "}
{"@t":"2019-10-21T08:21:08.0624920Z","@mt":"The culture specified {Culture} was not found in any configured sources for this service","@l":"Warning","Culture":"fi-FI","SourceContext":"Umbraco.Core.Services.Implement.LocalizedTextService","ProcessId":9500,"ProcessName":"iisexpress","ThreadId":11,"AppDomainId":2,"AppDomainAppId":"LMW3SVC2ROOT","MachineName":"LAPTOP-7D4JH2DL","Log4NetLevel":"WARN "}
{"@t":"2019-10-21T08:21:08.0679910Z","@mt":"The culture specified {Culture} was not found in any configured sources for this service","@l":"Warning","Culture":"fi-FI","SourceContext":"Umbraco.Core.Services.Implement.LocalizedTextService","ProcessId":9500,"ProcessName":"iisexpress","ThreadId":11,"AppDomainId":2,"AppDomainAppId":"LMW3SVC2ROOT","MachineName":"LAPTOP-7D4JH2DL","Log4NetLevel":"WARN "}
{"@t":"2019-10-21T08:21:08.0679910Z","@mt":"The culture specified {Culture} was not found in any configured sources for this service","@l":"Warning","Culture":"fi-FI","SourceContext":"Umbraco.Core.Services.Implement.LocalizedTextService","ProcessId":9500,"ProcessName":"iisexpress","ThreadId":11,"AppDomainId":2,"AppDomainAppId":"LMW3SVC2ROOT","MachineName":"LAPTOP-7D4JH2DL","Log4NetLevel":"WARN "}
{"@t":"2019-10-21T08:21:08.0689881Z","@mt":"The culture specified {Culture} was not found in any configured sources for this service","@l":"Warning","Culture":"fi-FI","SourceContext":"Umbraco.Core.Services.Implement.LocalizedTextService","ProcessId":9500,"ProcessName":"iisexpress","ThreadId":11,"AppDomainId":2,"AppDomainAppId":"LMW3SVC2ROOT","MachineName":"LAPTOP-7D4JH2DL","Log4NetLevel":"WARN "}
{"@t":"2019-10-21T08:21:08.0689881Z","@mt":"The culture specified {Culture} was not found in any configured sources for this service","@l":"Warning","Culture":"fi-FI","SourceContext":"Umbraco.Core.Services.Implement.LocalizedTextService","ProcessId":9500,"ProcessName":"iisexpress","ThreadId":11,"AppDomainId":2,"AppDomainAppId":"LMW3SVC2ROOT","MachineName":"LAPTOP-7D4JH2DL","Log4NetLevel":"WARN "}
{"@t":"2019-10-21T08:21:08.0906844Z","@mt":"The culture specified {Culture} was not found in any configured sources for this service","@l":"Warning","Culture":"fi-FI","SourceContext":"Umbraco.Core.Services.Implement.LocalizedTextService","ProcessId":9500,"ProcessName":"iisexpress","ThreadId":11,"AppDomainId":2,"AppDomainAppId":"LMW3SVC2ROOT","MachineName":"LAPTOP-7D4JH2DL","Log4NetLevel":"WARN "}
{"@t":"2019-10-21T08:21:08.0906844Z","@mt":"The culture specified {Culture} was not found in any configured sources for this service","@l":"Warning","Culture":"fi-FI","SourceContext":"Umbraco.Core.Services.Implement.LocalizedTextService","ProcessId":9500,"ProcessName":"iisexpress","ThreadId":11,"AppDomainId":2,"AppDomainAppId":"LMW3SVC2ROOT","MachineName":"LAPTOP-7D4JH2DL","Log4NetLevel":"WARN "}
{"@t":"2019-10-21T08:21:08.1069704Z","@mt":"The culture specified {Culture} was not found in any configured sources for this service","@l":"Warning","Culture":"fi-FI","SourceContext":"Umbraco.Core.Services.Implement.LocalizedTextService","ProcessId":9500,"ProcessName":"iisexpress","ThreadId":11,"AppDomainId":2,"AppDomainAppId":"LMW3SVC2ROOT","MachineName":"LAPTOP-7D4JH2DL","Log4NetLevel":"WARN "}
{"@t":"2019-10-21T08:21:10.8535129Z","@mt":"The culture specified {Culture} was not found in any configured sources for this service","@l":"Warning","Culture":"fi-FI","SourceContext":"Umbraco.Core.Services.Implement.LocalizedTextService","ProcessId":9500,"ProcessName":"iisexpress","ThreadId":11,"AppDomainId":2,"AppDomainAppId":"LMW3SVC2ROOT","MachineName":"LAPTOP-7D4JH2DL","Log4NetLevel":"WARN "}
{"@t":"2019-10-21T08:21:10.8535129Z","@mt":"The culture specified {Culture} was not found in any configured sources for this service","@l":"Warning","Culture":"fi-FI","SourceContext":"Umbraco.Core.Services.Implement.LocalizedTextService","ProcessId":9500,"ProcessName":"iisexpress","ThreadId":11,"AppDomainId":2,"AppDomainAppId":"LMW3SVC2ROOT","MachineName":"LAPTOP-7D4JH2DL","Log4NetLevel":"WARN "}
{"@t":"2019-10-21T08:21:10.8535129Z","@mt":"The culture specified {Culture} was not found in any configured sources for this service","@l":"Warning","Culture":"fi-FI","SourceContext":"Umbraco.Core.Services.Implement.LocalizedTextService","ProcessId":9500,"ProcessName":"iisexpress","ThreadId":11,"AppDomainId":2,"AppDomainAppId":"LMW3SVC2ROOT","MachineName":"LAPTOP-7D4JH2DL","Log4NetLevel":"WARN "}
{"@t":"2019-10-21T08:21:10.9878290Z","@mt":"The culture specified {Culture} was not found in any configured sources for this service","@l":"Warning","Culture":"fi-FI","SourceContext":"Umbraco.Core.Services.Implement.LocalizedTextService","ProcessId":9500,"ProcessName":"iisexpress","ThreadId":11,"AppDomainId":2,"AppDomainAppId":"LMW3SVC2ROOT","MachineName":"LAPTOP-7D4JH2DL","Log4NetLevel":"WARN "}
{"@t":"2019-10-21T08:21:10.9878290Z","@mt":"The culture specified {Culture} was not found in any configured sources for this service","@l":"Warning","Culture":"fi-FI","SourceContext":"Umbraco.Core.Services.Implement.LocalizedTextService","ProcessId":9500,"ProcessName":"iisexpress","ThreadId":11,"AppDomainId":2,"AppDomainAppId":"LMW3SVC2ROOT","MachineName":"LAPTOP-7D4JH2DL","Log4NetLevel":"WARN "}
{"@t":"2019-10-21T08:21:10.9878290Z","@mt":"The culture specified {Culture} was not found in any configured sources for this service","@l":"Warning","Culture":"fi-FI","SourceContext":"Umbraco.Core.Services.Implement.LocalizedTextService","ProcessId":9500,"ProcessName":"iisexpress","ThreadId":11,"AppDomainId":2,"AppDomainAppId":"LMW3SVC2ROOT","MachineName":"LAPTOP-7D4JH2DL","Log4NetLevel":"WARN "}
{"@t":"2019-10-21T08:21:11.0760607Z","@mt":"The culture specified {Culture} was not found in any configured sources for this service","@l":"Warning","Culture":"fi-FI","SourceContext":"Umbraco.Core.Services.Implement.LocalizedTextService","ProcessId":9500,"ProcessName":"iisexpress","ThreadId":11,"AppDomainId":2,"AppDomainAppId":"LMW3SVC2ROOT","MachineName":"LAPTOP-7D4JH2DL","Log4NetLevel":"WARN "}
{"@t":"2019-10-21T08:21:11.0760607Z","@mt":"The culture specified {Culture} was not found in any configured sources for this service","@l":"Warning","Culture":"fi-FI","SourceContext":"Umbraco.Core.Services.Implement.LocalizedTextService","ProcessId":9500,"ProcessName":"iisexpress","ThreadId":11,"AppDomainId":2,"AppDomainAppId":"LMW3SVC2ROOT","MachineName":"LAPTOP-7D4JH2DL","Log4NetLevel":"WARN "}
{"@t":"2019-10-21T08:21:11.0760607Z","@mt":"The culture specified {Culture} was not found in any configured sources for this service","@l":"Warning","Culture":"fi-FI","SourceContext":"Umbraco.Core.Services.Implement.LocalizedTextService","ProcessId":9500,"ProcessName":"iisexpress","ThreadId":11,"AppDomainId":2,"AppDomainAppId":"LMW3SVC2ROOT","MachineName":"LAPTOP-7D4JH2DL","Log4NetLevel":"WARN "}
{"@t":"2019-10-21T08:21:11.1653360Z","@mt":"The culture specified {Culture} was not found in any configured sources for this service","@l":"Warning","Culture":"fi-FI","SourceContext":"Umbraco.Core.Services.Implement.LocalizedTextService","ProcessId":9500,"ProcessName":"iisexpress","ThreadId":11,"AppDomainId":2,"AppDomainAppId":"LMW3SVC2ROOT","MachineName":"LAPTOP-7D4JH2DL","Log4NetLevel":"WARN "}
{"@t":"2019-10-21T08:21:11.2232323Z","@mt":"The culture specified {Culture} was not found in any configured sources for this service","@l":"Warning","Culture":"fi-FI","SourceContext":"Umbraco.Core.Services.Implement.LocalizedTextService","ProcessId":9500,"ProcessName":"iisexpress","ThreadId":11,"AppDomainId":2,"AppDomainAppId":"LMW3SVC2ROOT","MachineName":"LAPTOP-7D4JH2DL","Log4NetLevel":"WARN "}
{"@t":"2019-10-21T08:21:11.2232323Z","@mt":"The culture specified {Culture} was not found in any configured sources for this service","@l":"Warning","Culture":"fi-FI","SourceContext":"Umbraco.Core.Services.Implement.LocalizedTextService","ProcessId":9500,"ProcessName":"iisexpress","ThreadId":11,"AppDomainId":2,"AppDomainAppId":"LMW3SVC2ROOT","MachineName":"LAPTOP-7D4JH2DL","Log4NetLevel":"WARN "}
{"@t":"2019-10-21T08:21:11.2232323Z","@mt":"The culture specified {Culture} was not found in any configured sources for this service","@l":"Warning","Culture":"fi-FI","SourceContext":"Umbraco.Core.Services.Implement.LocalizedTextService","ProcessId":9500,"ProcessName":"iisexpress","ThreadId":11,"AppDomainId":2,"AppDomainAppId":"LMW3SVC2ROOT","MachineName":"LAPTOP-7D4JH2DL","Log4NetLevel":"WARN "}
{"@t":"2019-10-21T08:21:11.2241114Z","@mt":"The culture specified {Culture} was not found in any configured sources for this service","@l":"Warning","Culture":"fi-FI","SourceContext":"Umbraco.Core.Services.Implement.LocalizedTextService","ProcessId":9500,"ProcessName":"iisexpress","ThreadId":11,"AppDomainId":2,"AppDomainAppId":"LMW3SVC2ROOT","MachineName":"LAPTOP-7D4JH2DL","Log4NetLevel":"WARN "}
{"@t":"2019-10-21T08:21:11.2256476Z","@mt":"The culture specified {Culture} was not found in any configured sources for this service","@l":"Warning","Culture":"fi-FI","SourceContext":"Umbraco.Core.Services.Implement.LocalizedTextService","ProcessId":9500,"ProcessName":"iisexpress","ThreadId":11,"AppDomainId":2,"AppDomainAppId":"LMW3SVC2ROOT","MachineName":"LAPTOP-7D4JH2DL","Log4NetLevel":"WARN "}
{"@t":"2019-10-21T08:21:11.4470375Z","@mt":"The culture specified {Culture} was not found in any configured sources for this service","@l":"Warning","Culture":"fi-FI","SourceContext":"Umbraco.Core.Services.Implement.LocalizedTextService","ProcessId":9500,"ProcessName":"iisexpress","ThreadId":11,"AppDomainId":2,"AppDomainAppId":"LMW3SVC2ROOT","MachineName":"LAPTOP-7D4JH2DL","Log4NetLevel":"WARN "}
{"@t":"2019-10-21T08:21:11.4513272Z","@mt":"Scheduled health check results:","SourceContext":"Umbraco.Web.HealthCheck.HealthCheckResults","ProcessId":9500,"ProcessName":"iisexpress","ThreadId":11,"AppDomainId":2,"AppDomainAppId":"LMW3SVC2ROOT","MachineName":"LAPTOP-7D4JH2DL","Log4NetLevel":"INFO "}
{"@t":"2019-10-21T08:21:11.4513272Z","@mt":"Checks for '{HealthCheckName}' all completed successfully.","HealthCheckName":"Folder & File Permissions","SourceContext":"Umbraco.Web.HealthCheck.HealthCheckResults","ProcessId":9500,"ProcessName":"iisexpress","ThreadId":11,"AppDomainId":2,"AppDomainAppId":"LMW3SVC2ROOT","MachineName":"LAPTOP-7D4JH2DL","Log4NetLevel":"INFO "}
{"@t":"2019-10-21T08:21:11.4513272Z","@mt":"Result for {HealthCheckName}: {HealthCheckResult}, Message: '{HealthCheckMessage}'","HealthCheckName":"Folder & File Permissions","HealthCheckResult":"Success","HealthCheckMessage":"[folderPermissionsCheckMessage]","SourceContext":"Umbraco.Web.HealthCheck.HealthCheckResults","ProcessId":9500,"ProcessName":"iisexpress","ThreadId":11,"AppDomainId":2,"AppDomainAppId":"LMW3SVC2ROOT","MachineName":"LAPTOP-7D4JH2DL","Log4NetLevel":"INFO "}
{"@t":"2019-10-21T08:21:11.4513272Z","@mt":"Result for {HealthCheckName}: {HealthCheckResult}, Message: '{HealthCheckMessage}'","HealthCheckName":"Folder & File Permissions","HealthCheckResult":"Success","HealthCheckMessage":"[filePermissionsCheckMessage]","SourceContext":"Umbraco.Web.HealthCheck.HealthCheckResults","ProcessId":9500,"ProcessName":"iisexpress","ThreadId":11,"AppDomainId":2,"AppDomainAppId":"LMW3SVC2ROOT","MachineName":"LAPTOP-7D4JH2DL","Log4NetLevel":"INFO "}
{"@t":"2019-10-21T08:21:11.4513272Z","@mt":"Checks for '{HealthCheckName}' completed with errors.","@l":"Warning","HealthCheckName":"SMTP Settings","SourceContext":"Umbraco.Web.HealthCheck.HealthCheckResults","ProcessId":9500,"ProcessName":"iisexpress","ThreadId":11,"AppDomainId":2,"AppDomainAppId":"LMW3SVC2ROOT","MachineName":"LAPTOP-7D4JH2DL","Log4NetLevel":"WARN "}
{"@t":"2019-10-21T08:21:11.4513272Z","@mt":"Result for {HealthCheckName}: {HealthCheckResult}, Message: '{HealthCheckMessage}'","HealthCheckName":"SMTP Settings","HealthCheckResult":"Error","HealthCheckMessage":"[smtpMailSettingsHostNotConfigured]","SourceContext":"Umbraco.Web.HealthCheck.HealthCheckResults","ProcessId":9500,"ProcessName":"iisexpress","ThreadId":11,"AppDomainId":2,"AppDomainAppId":"LMW3SVC2ROOT","MachineName":"LAPTOP-7D4JH2DL","Log4NetLevel":"INFO "}
{"@t":"2019-10-21T08:21:11.4513272Z","@mt":"Checks for '{HealthCheckName}' completed with errors.","@l":"Warning","HealthCheckName":"Macro errors","SourceContext":"Umbraco.Web.HealthCheck.HealthCheckResults","ProcessId":9500,"ProcessName":"iisexpress","ThreadId":11,"AppDomainId":2,"AppDomainAppId":"LMW3SVC2ROOT","MachineName":"LAPTOP-7D4JH2DL","Log4NetLevel":"WARN "}
{"@t":"2019-10-21T08:21:11.4513272Z","@mt":"Result for {HealthCheckName}: {HealthCheckResult}, Message: '{HealthCheckMessage}'","HealthCheckName":"Macro errors","HealthCheckResult":"Error","HealthCheckMessage":"[macroErrorModeCheckErrorMessage]","SourceContext":"Umbraco.Web.HealthCheck.HealthCheckResults","ProcessId":9500,"ProcessName":"iisexpress","ThreadId":11,"AppDomainId":2,"AppDomainAppId":"LMW3SVC2ROOT","MachineName":"LAPTOP-7D4JH2DL","Log4NetLevel":"INFO "}
{"@t":"2019-10-21T08:21:11.4513272Z","@mt":"Checks for '{HealthCheckName}' completed with errors.","@l":"Warning","HealthCheckName":"Notification Email Settings","SourceContext":"Umbraco.Web.HealthCheck.HealthCheckResults","ProcessId":9500,"ProcessName":"iisexpress","ThreadId":11,"AppDomainId":2,"AppDomainAppId":"LMW3SVC2ROOT","MachineName":"LAPTOP-7D4JH2DL","Log4NetLevel":"WARN "}
{"@t":"2019-10-21T08:21:11.4513272Z","@mt":"Result for {HealthCheckName}: {HealthCheckResult}, Message: '{HealthCheckMessage}'","HealthCheckName":"Notification Email Settings","HealthCheckResult":"Error","HealthCheckMessage":"[notificationEmailsCheckErrorMessage]","SourceContext":"Umbraco.Web.HealthCheck.HealthCheckResults","ProcessId":9500,"ProcessName":"iisexpress","ThreadId":11,"AppDomainId":2,"AppDomainAppId":"LMW3SVC2ROOT","MachineName":"LAPTOP-7D4JH2DL","Log4NetLevel":"INFO "}
{"@t":"2019-10-21T08:21:11.4513272Z","@mt":"Checks for '{HealthCheckName}' all completed successfully.","HealthCheckName":"Try Skip IIS Custom Errors","SourceContext":"Umbraco.Web.HealthCheck.HealthCheckResults","ProcessId":9500,"ProcessName":"iisexpress","ThreadId":11,"AppDomainId":2,"AppDomainAppId":"LMW3SVC2ROOT","MachineName":"LAPTOP-7D4JH2DL","Log4NetLevel":"INFO "}
{"@t":"2019-10-21T08:21:11.4513272Z","@mt":"Result for {HealthCheckName}: {HealthCheckResult}, Message: '{HealthCheckMessage}'","HealthCheckName":"Try Skip IIS Custom Errors","HealthCheckResult":"Success","HealthCheckMessage":"[trySkipIisCustomErrorsCheckSuccessMessage]","SourceContext":"Umbraco.Web.HealthCheck.HealthCheckResults","ProcessId":9500,"ProcessName":"iisexpress","ThreadId":11,"AppDomainId":2,"AppDomainAppId":"LMW3SVC2ROOT","MachineName":"LAPTOP-7D4JH2DL","Log4NetLevel":"INFO "}
{"@t":"2019-10-21T08:21:11.4513272Z","@mt":"Checks for '{HealthCheckName}' all completed successfully.","HealthCheckName":"Custom Errors","SourceContext":"Umbraco.Web.HealthCheck.HealthCheckResults","ProcessId":9500,"ProcessName":"iisexpress","ThreadId":11,"AppDomainId":2,"AppDomainAppId":"LMW3SVC2ROOT","MachineName":"LAPTOP-7D4JH2DL","Log4NetLevel":"INFO "}
{"@t":"2019-10-21T08:21:11.4513272Z","@mt":"Result for {HealthCheckName}: {HealthCheckResult}, Message: '{HealthCheckMessage}'","HealthCheckName":"Custom Errors","HealthCheckResult":"Success","HealthCheckMessage":"[customErrorsCheckSuccessMessage]","SourceContext":"Umbraco.Web.HealthCheck.HealthCheckResults","ProcessId":9500,"ProcessName":"iisexpress","ThreadId":11,"AppDomainId":2,"AppDomainAppId":"LMW3SVC2ROOT","MachineName":"LAPTOP-7D4JH2DL","Log4NetLevel":"INFO "}
{"@t":"2019-10-21T08:21:11.4513272Z","@mt":"Checks for '{HealthCheckName}' all completed successfully.","HealthCheckName":"Trace Mode","SourceContext":"Umbraco.Web.HealthCheck.HealthCheckResults","ProcessId":9500,"ProcessName":"iisexpress","ThreadId":11,"AppDomainId":2,"AppDomainAppId":"LMW3SVC2ROOT","MachineName":"LAPTOP-7D4JH2DL","Log4NetLevel":"INFO "}
{"@t":"2019-10-21T08:21:11.4513272Z","@mt":"Result for {HealthCheckName}: {HealthCheckResult}, Message: '{HealthCheckMessage}'","HealthCheckName":"Trace Mode","HealthCheckResult":"Success","HealthCheckMessage":"[traceModeCheckSuccessMessage]","SourceContext":"Umbraco.Web.HealthCheck.HealthCheckResults","ProcessId":9500,"ProcessName":"iisexpress","ThreadId":11,"AppDomainId":2,"AppDomainAppId":"LMW3SVC2ROOT","MachineName":"LAPTOP-7D4JH2DL","Log4NetLevel":"INFO "}
{"@t":"2019-10-21T08:21:11.4513272Z","@mt":"Checks for '{HealthCheckName}' all completed successfully.","HealthCheckName":"Debug Compilation Mode","SourceContext":"Umbraco.Web.HealthCheck.HealthCheckResults","ProcessId":9500,"ProcessName":"iisexpress","ThreadId":11,"AppDomainId":2,"AppDomainAppId":"LMW3SVC2ROOT","MachineName":"LAPTOP-7D4JH2DL","Log4NetLevel":"INFO "}
{"@t":"2019-10-21T08:21:11.4513272Z","@mt":"Result for {HealthCheckName}: {HealthCheckResult}, Message: '{HealthCheckMessage}'","HealthCheckName":"Debug Compilation Mode","HealthCheckResult":"Success","HealthCheckMessage":"[compilationDebugCheckSuccessMessage]","SourceContext":"Umbraco.Web.HealthCheck.HealthCheckResults","ProcessId":9500,"ProcessName":"iisexpress","ThreadId":11,"AppDomainId":2,"AppDomainAppId":"LMW3SVC2ROOT","MachineName":"LAPTOP-7D4JH2DL","Log4NetLevel":"INFO "}
{"@t":"2019-10-21T08:21:11.4513272Z","@mt":"Checks for '{HealthCheckName}' completed with errors.","@l":"Warning","HealthCheckName":"Cross-site scripting Protection (X-XSS-Protection header)","SourceContext":"Umbraco.Web.HealthCheck.HealthCheckResults","ProcessId":9500,"ProcessName":"iisexpress","ThreadId":11,"AppDomainId":2,"AppDomainAppId":"LMW3SVC2ROOT","MachineName":"LAPTOP-7D4JH2DL","Log4NetLevel":"WARN "}
{"@t":"2019-10-21T08:21:11.4513272Z","@mt":"Result for {HealthCheckName}: {HealthCheckResult}, Message: '{HealthCheckMessage}'","HealthCheckName":"Cross-site scripting Protection (X-XSS-Protection header)","HealthCheckResult":"Error","HealthCheckMessage":"[xssProtectionCheckHeaderNotFound]","SourceContext":"Umbraco.Web.HealthCheck.HealthCheckResults","ProcessId":9500,"ProcessName":"iisexpress","ThreadId":11,"AppDomainId":2,"AppDomainAppId":"LMW3SVC2ROOT","MachineName":"LAPTOP-7D4JH2DL","Log4NetLevel":"INFO "}
{"@t":"2019-10-21T08:21:11.4513272Z","@mt":"Checks for '{HealthCheckName}' completed with errors.","@l":"Warning","HealthCheckName":"Cookie hijacking and protocol downgrade attacks Protection (Strict-Transport-Security Header (HSTS))","SourceContext":"Umbraco.Web.HealthCheck.HealthCheckResults","ProcessId":9500,"ProcessName":"iisexpress","ThreadId":11,"AppDomainId":2,"AppDomainAppId":"LMW3SVC2ROOT","MachineName":"LAPTOP-7D4JH2DL","Log4NetLevel":"WARN "}
{"@t":"2019-10-21T08:21:11.4513272Z","@mt":"Result for {HealthCheckName}: {HealthCheckResult}, Message: '{HealthCheckMessage}'","HealthCheckName":"Cookie hijacking and protocol downgrade attacks Protection (Strict-Transport-Security Header (HSTS))","HealthCheckResult":"Error","HealthCheckMessage":"[hSTSCheckHeaderNotFound]","SourceContext":"Umbraco.Web.HealthCheck.HealthCheckResults","ProcessId":9500,"ProcessName":"iisexpress","ThreadId":11,"AppDomainId":2,"AppDomainAppId":"LMW3SVC2ROOT","MachineName":"LAPTOP-7D4JH2DL","Log4NetLevel":"INFO "}
{"@t":"2019-10-21T08:21:11.4513272Z","@mt":"Checks for '{HealthCheckName}' completed with errors.","@l":"Warning","HealthCheckName":"Content/MIME Sniffing Protection","SourceContext":"Umbraco.Web.HealthCheck.HealthCheckResults","ProcessId":9500,"ProcessName":"iisexpress","ThreadId":11,"AppDomainId":2,"AppDomainAppId":"LMW3SVC2ROOT","MachineName":"LAPTOP-7D4JH2DL","Log4NetLevel":"WARN "}
{"@t":"2019-10-21T08:21:11.4513272Z","@mt":"Result for {HealthCheckName}: {HealthCheckResult}, Message: '{HealthCheckMessage}'","HealthCheckName":"Content/MIME Sniffing Protection","HealthCheckResult":"Error","HealthCheckMessage":"[noSniffCheckHeaderNotFound]","SourceContext":"Umbraco.Web.HealthCheck.HealthCheckResults","ProcessId":9500,"ProcessName":"iisexpress","ThreadId":11,"AppDomainId":2,"AppDomainAppId":"LMW3SVC2ROOT","MachineName":"LAPTOP-7D4JH2DL","Log4NetLevel":"INFO "}
{"@t":"2019-10-21T08:21:11.4513272Z","@mt":"Checks for '{HealthCheckName}' all completed successfully.","HealthCheckName":"Excessive Headers","SourceContext":"Umbraco.Web.HealthCheck.HealthCheckResults","ProcessId":9500,"ProcessName":"iisexpress","ThreadId":11,"AppDomainId":2,"AppDomainAppId":"LMW3SVC2ROOT","MachineName":"LAPTOP-7D4JH2DL","Log4NetLevel":"INFO "}
{"@t":"2019-10-21T08:21:11.4523119Z","@mt":"Result for {HealthCheckName}: {HealthCheckResult}, Message: '{HealthCheckMessage}'","HealthCheckName":"Excessive Headers","HealthCheckResult":"Success","HealthCheckMessage":"[excessiveHeadersNotFound]","SourceContext":"Umbraco.Web.HealthCheck.HealthCheckResults","ProcessId":9500,"ProcessName":"iisexpress","ThreadId":11,"AppDomainId":2,"AppDomainAppId":"LMW3SVC2ROOT","MachineName":"LAPTOP-7D4JH2DL","Log4NetLevel":"INFO "}
{"@t":"2019-10-21T08:21:11.4523119Z","@mt":"Checks for '{HealthCheckName}' completed with errors.","@l":"Warning","HealthCheckName":"Click-Jacking Protection","SourceContext":"Umbraco.Web.HealthCheck.HealthCheckResults","ProcessId":9500,"ProcessName":"iisexpress","ThreadId":11,"AppDomainId":2,"AppDomainAppId":"LMW3SVC2ROOT","MachineName":"LAPTOP-7D4JH2DL","Log4NetLevel":"WARN "}
{"@t":"2019-10-21T08:21:11.4523119Z","@mt":"Result for {HealthCheckName}: {HealthCheckResult}, Message: '{HealthCheckMessage}'","HealthCheckName":"Click-Jacking Protection","HealthCheckResult":"Error","HealthCheckMessage":"[clickJackingCheckHeaderNotFound]","SourceContext":"Umbraco.Web.HealthCheck.HealthCheckResults","ProcessId":9500,"ProcessName":"iisexpress","ThreadId":11,"AppDomainId":2,"AppDomainAppId":"LMW3SVC2ROOT","MachineName":"LAPTOP-7D4JH2DL","Log4NetLevel":"INFO "}
{"@t":"2019-10-21T08:21:11.4523119Z","@mt":"Checks for '{HealthCheckName}' completed with errors.","@l":"Warning","HealthCheckName":"HTTPS Configuration","SourceContext":"Umbraco.Web.HealthCheck.HealthCheckResults","ProcessId":9500,"ProcessName":"iisexpress","ThreadId":11,"AppDomainId":2,"AppDomainAppId":"LMW3SVC2ROOT","MachineName":"LAPTOP-7D4JH2DL","Log4NetLevel":"WARN "}
{"@t":"2019-10-21T08:21:11.4523119Z","@mt":"Result for {HealthCheckName}: {HealthCheckResult}, Message: '{HealthCheckMessage}'","HealthCheckName":"HTTPS Configuration","HealthCheckResult":"Error","HealthCheckMessage":"[httpsCheckIsCurrentSchemeHttps]","SourceContext":"Umbraco.Web.HealthCheck.HealthCheckResults","ProcessId":9500,"ProcessName":"iisexpress","ThreadId":11,"AppDomainId":2,"AppDomainAppId":"LMW3SVC2ROOT","MachineName":"LAPTOP-7D4JH2DL","Log4NetLevel":"INFO "}
{"@t":"2019-10-21T08:21:11.4523119Z","@mt":"Result for {HealthCheckName}: {HealthCheckResult}, Message: '{HealthCheckMessage}'","HealthCheckName":"HTTPS Configuration","HealthCheckResult":"Info","HealthCheckMessage":"[httpsCheckConfigurationRectifyNotPossible]","SourceContext":"Umbraco.Web.HealthCheck.HealthCheckResults","ProcessId":9500,"ProcessName":"iisexpress","ThreadId":11,"AppDomainId":2,"AppDomainAppId":"LMW3SVC2ROOT","MachineName":"LAPTOP-7D4JH2DL","Log4NetLevel":"INFO "}
{"@t":"2019-10-21T08:21:11.4523119Z","@mt":"Result for {HealthCheckName}: {HealthCheckResult}, Message: '{HealthCheckMessage}'","HealthCheckName":"HTTPS Configuration","HealthCheckResult":"Error","HealthCheckMessage":"[healthCheckInvalidUrl]","SourceContext":"Umbraco.Web.HealthCheck.HealthCheckResults","ProcessId":9500,"ProcessName":"iisexpress","ThreadId":11,"AppDomainId":2,"AppDomainAppId":"LMW3SVC2ROOT","MachineName":"LAPTOP-7D4JH2DL","Log4NetLevel":"INFO "}
{"@t":"2019-10-21T08:21:21.0720965Z","@mt":"[{EventType}] Event Id: {EventId}, State: {State}","EventType":"Information","EventId":0,"State":"Login attempt succeeded for username taneli.juga@hyvanmielenpelit.fi from IP address ::1","SourceContext":"Umbraco.Core.Logging.OwinLogger","ProcessId":9500,"ProcessName":"iisexpress","ThreadId":10,"AppDomainId":2,"AppDomainAppId":"LMW3SVC2ROOT","MachineName":"LAPTOP-7D4JH2DL","Log4NetLevel":"INFO ","HttpRequestNumber":4,"HttpRequestId":"53d8671f-6d89-49d4-8bff-08bf3dd6a8c4"}
{"@t":"2019-10-21T08:21:21.0740909Z","@mt":"[{EventType}] Event Id: {EventId}, State: {State}","EventType":"Information","EventId":0,"State":"User: taneli.juga@hyvanmielenpelit.fi logged in from IP address ::1","SourceContext":"Umbraco.Core.Logging.OwinLogger","ProcessId":9500,"ProcessName":"iisexpress","ThreadId":10,"AppDomainId":2,"AppDomainAppId":"LMW3SVC2ROOT","MachineName":"LAPTOP-7D4JH2DL","Log4NetLevel":"INFO ","HttpRequestNumber":4,"HttpRequestId":"53d8671f-6d89-49d4-8bff-08bf3dd6a8c4"}
{"@t":"2019-10-21T08:21:23.8340794Z","@mt":"Error getting dashboard CSS from {Url}","@l":"Error","@x":"System.Net.WebException: The remote name could not be resolved: 'dashboard.umbraco.org'\r\n   kohteessa System.Net.HttpWebRequest.EndGetResponse(IAsyncResult asyncResult)\r\n   kohteessa System.Net.Http.HttpClientHandler.GetResponseCallback(IAsyncResult ar)","Url":"https://dashboard.umbraco.org/css/dashboard.css?section=content","SourceContext":"Umbraco.Web.Editors.DashboardController","ProcessId":9500,"ProcessName":"iisexpress","ThreadId":20,"AppDomainId":2,"AppDomainAppId":"LMW3SVC2ROOT","MachineName":"LAPTOP-7D4JH2DL","Log4NetLevel":"ERROR","HttpRequestNumber":5,"HttpRequestId":"f4680f3f-0c9a-483a-99fb-4a429181fea3"}
{"@t":"2019-10-21T08:21:23.8381810Z","@mt":"Error getting dashboard content from {Url}","@l":"Error","@x":"System.Net.WebException: The remote name could not be resolved: 'dashboard.umbraco.org'\r\n   kohteessa System.Net.HttpWebRequest.EndGetResponse(IAsyncResult asyncResult)\r\n   kohteessa System.Net.Http.HttpClientHandler.GetResponseCallback(IAsyncResult ar)","Url":"https://dashboard.umbraco.org/content?section=content&allowed=content,forms,media,member,packages,settings,users&lang=en-US&version=8.1.5","SourceContext":"Umbraco.Web.Editors.DashboardController","ProcessId":9500,"ProcessName":"iisexpress","ThreadId":21,"AppDomainId":2,"AppDomainAppId":"LMW3SVC2ROOT","MachineName":"LAPTOP-7D4JH2DL","Log4NetLevel":"ERROR","HttpRequestNumber":6,"HttpRequestId":"b7af9700-0815-4796-8bf1-0bc745385136"}
{"@t":"2019-10-21T08:55:58.7076101Z","@mt":"[{EventType}] Event Id: {EventId}, State: {State}","EventType":"Information","EventId":0,"State":"Login attempt succeeded for username taneli.juga@hyvanmielenpelit.fi from IP address ::1","SourceContext":"Umbraco.Core.Logging.OwinLogger","ProcessId":9500,"ProcessName":"iisexpress","ThreadId":42,"AppDomainId":2,"AppDomainAppId":"LMW3SVC2ROOT","MachineName":"LAPTOP-7D4JH2DL","Log4NetLevel":"INFO ","HttpRequestNumber":7,"HttpRequestId":"65b8be6c-5d9f-4e18-a356-e8271eb5762f"}
{"@t":"2019-10-21T08:55:58.7086068Z","@mt":"[{EventType}] Event Id: {EventId}, State: {State}","EventType":"Information","EventId":0,"State":"User: taneli.juga@hyvanmielenpelit.fi logged in from IP address ::1","SourceContext":"Umbraco.Core.Logging.OwinLogger","ProcessId":9500,"ProcessName":"iisexpress","ThreadId":42,"AppDomainId":2,"AppDomainAppId":"LMW3SVC2ROOT","MachineName":"LAPTOP-7D4JH2DL","Log4NetLevel":"INFO ","HttpRequestNumber":7,"HttpRequestId":"65b8be6c-5d9f-4e18-a356-e8271eb5762f"}
{"@t":"2019-10-21T09:00:34.4619521Z","@mt":"An unhandled exception occurred","@l":"Error","@x":"System.Web.HttpCompileException (0x80004005): C:\\Users\\tanel\\source\\repos\\gnollhack-website3\\gnollhack-website\\gnollhack2\\Views\\ItemCategory.cshtml(20): error CS0103: The name 'itemClass' does not exist in the current context\r\n   kohteessa System.Web.Compilation.AssemblyBuilder.Compile()\r\n   kohteessa System.Web.Compilation.BuildProvidersCompiler.PerformBuild()\r\n   kohteessa System.Web.Compilation.BuildManager.CompileWebFile(VirtualPath virtualPath)\r\n   kohteessa System.Web.Compilation.BuildManager.GetVPathBuildResultInternal(VirtualPath virtualPath, Boolean noBuild, Boolean allowCrossApp, Boolean allowBuildInPrecompile, Boolean throwIfNotFound, Boolean ensureIsUpToDate)\r\n   kohteessa System.Web.Compilation.BuildManager.GetVPathBuildResultWithNoAssert(HttpContext context, VirtualPath virtualPath, Boolean noBuild, Boolean allowCrossApp, Boolean allowBuildInPrecompile, Boolean throwIfNotFound, Boolean ensureIsUpToDate)\r\n   kohteessa System.Web.Compilation.BuildManager.GetVirtualPathObjectFactory(VirtualPath virtualPath, HttpContext context, Boolean allowCrossApp, Boolean throwIfNotFound)\r\n   kohteessa System.Web.Compilation.BuildManager.GetCompiledType(VirtualPath virtualPath)\r\n   kohteessa System.Web.Compilation.BuildManager.GetCompiledType(String virtualPath)\r\n   kohteessa System.Web.Mvc.BuildManagerWrapper.System.Web.Mvc.IBuildManager.GetCompiledType(String virtualPath)\r\n   kohteessa System.Web.Mvc.BuildManagerCompiledView.Render(ViewContext viewContext, TextWriter writer)\r\n   kohteessa Umbraco.Web.Mvc.ProfilingView.Render(ViewContext viewContext, TextWriter writer) tiedostossa d:\\a\\1\\s\\src\\Umbraco.Web\\Mvc\\ProfilingView.cs:rivillä 25\r\n   kohteessa System.Web.Mvc.ViewResultBase.ExecuteResult(ControllerContext context)\r\n   kohteessa System.Web.Mvc.ControllerActionInvoker.InvokeActionResult(ControllerContext controllerContext, ActionResult actionResult)\r\n   kohteessa System.Web.Mvc.ControllerActionInvoker.InvokeActionResultFilterRecursive(IList`1 filters, Int32 filterIndex, ResultExecutingContext preContext, ControllerContext controllerContext, ActionResult actionResult)\r\n   kohteessa System.Web.Mvc.ControllerActionInvoker.InvokeActionResultFilterRecursive(IList`1 filters, Int32 filterIndex, ResultExecutingContext preContext, ControllerContext controllerContext, ActionResult actionResult)\r\n   kohteessa System.Web.Mvc.ControllerActionInvoker.InvokeActionResultFilterRecursive(IList`1 filters, Int32 filterIndex, ResultExecutingContext preContext, ControllerContext controllerContext, ActionResult actionResult)\r\n   kohteessa System.Web.Mvc.ControllerActionInvoker.InvokeActionResultFilterRecursive(IList`1 filters, Int32 filterIndex, ResultExecutingContext preContext, ControllerContext controllerContext, ActionResult actionResult)\r\n   kohteessa System.Web.Mvc.ControllerActionInvoker.InvokeActionResultWithFilters(ControllerContext controllerContext, IList`1 filters, ActionResult actionResult)\r\n   kohteessa System.Web.Mvc.Async.AsyncControllerActionInvoker.<>c__DisplayClass3_6.<BeginInvokeAction>b__4()\r\n   kohteessa System.Web.Mvc.Async.AsyncControllerActionInvoker.<>c__DisplayClass3_1.<BeginInvokeAction>b__1(IAsyncResult asyncResult)\r\n   kohteessa System.Web.Mvc.Async.AsyncResultWrapper.WrappedAsyncResult`1.CallEndDelegate(IAsyncResult asyncResult)\r\n   kohteessa System.Web.Mvc.Async.AsyncResultWrapper.WrappedAsyncResultBase`1.End()\r\n   kohteessa System.Web.Mvc.Async.AsyncControllerActionInvoker.EndInvokeAction(IAsyncResult asyncResult)\r\n   kohteessa System.Web.Mvc.Controller.<>c.<BeginExecuteCore>b__152_1(IAsyncResult asyncResult, ExecuteCoreState innerState)\r\n   kohteessa System.Web.Mvc.Async.AsyncResultWrapper.WrappedAsyncVoid`1.CallEndDelegate(IAsyncResult asyncResult)\r\n   kohteessa System.Web.Mvc.Async.AsyncResultWrapper.WrappedAsyncResultBase`1.End()\r\n   kohteessa System.Web.Mvc.Controller.EndExecuteCore(IAsyncResult asyncResult)\r\n   kohteessa System.Web.Mvc.Controller.<>c.<BeginExecute>b__151_2(IAsyncResult asyncResult, Controller controller)\r\n   kohteessa System.Web.Mvc.Async.AsyncResultWrapper.WrappedAsyncVoid`1.CallEndDelegate(IAsyncResult asyncResult)\r\n   kohteessa System.Web.Mvc.Async.AsyncResultWrapper.WrappedAsyncResultBase`1.End()\r\n   kohteessa System.Web.Mvc.Controller.EndExecute(IAsyncResult asyncResult)\r\n   kohteessa System.Web.Mvc.Controller.System.Web.Mvc.Async.IAsyncController.EndExecute(IAsyncResult asyncResult)\r\n   kohteessa System.Web.Mvc.MvcHandler.<>c.<BeginProcessRequest>b__20_1(IAsyncResult asyncResult, ProcessRequestState innerState)\r\n   kohteessa System.Web.Mvc.Async.AsyncResultWrapper.WrappedAsyncVoid`1.CallEndDelegate(IAsyncResult asyncResult)\r\n   kohteessa System.Web.Mvc.Async.AsyncResultWrapper.WrappedAsyncResultBase`1.End()\r\n   kohteessa System.Web.Mvc.MvcHandler.EndProcessRequest(IAsyncResult asyncResult)\r\n   kohteessa System.Web.Mvc.MvcHandler.System.Web.IHttpAsyncHandler.EndProcessRequest(IAsyncResult result)\r\n   kohteessa System.Web.HttpApplication.CallHandlerExecutionStep.System.Web.HttpApplication.IExecutionStep.Execute()\r\n   kohteessa System.Web.HttpApplication.ExecuteStepImpl(IExecutionStep step)\r\n   kohteessa System.Web.HttpApplication.ExecuteStep(IExecutionStep step, Boolean& completedSynchronously)","SourceContext":"Umbraco.Web.UmbracoApplicationBase","ProcessId":9500,"ProcessName":"iisexpress","ThreadId":25,"AppDomainId":2,"AppDomainAppId":"LMW3SVC2ROOT","MachineName":"LAPTOP-7D4JH2DL","Log4NetLevel":"ERROR","HttpSessionId":"wlrtn5nprtg2lw5xicrdnum2","HttpRequestNumber":8,"HttpRequestId":"16917a05-0549-4ddc-b33b-aa27771494e2"}
{"@t":"2019-10-21T09:01:17.4300608Z","@mt":"An unhandled exception occurred","@l":"Error","@x":"System.Web.HttpCompileException (0x80004005): C:\\Users\\tanel\\source\\repos\\gnollhack-website3\\gnollhack-website\\gnollhack2\\Views\\ItemCategory.cshtml(20): error CS0103: The name 'itemClass' does not exist in the current context\r\n   kohteessa System.Web.Compilation.AssemblyBuilder.Compile()\r\n   kohteessa System.Web.Compilation.BuildProvidersCompiler.PerformBuild()\r\n   kohteessa System.Web.Compilation.BuildManager.CompileWebFile(VirtualPath virtualPath)\r\n   kohteessa System.Web.Compilation.BuildManager.GetVPathBuildResultInternal(VirtualPath virtualPath, Boolean noBuild, Boolean allowCrossApp, Boolean allowBuildInPrecompile, Boolean throwIfNotFound, Boolean ensureIsUpToDate)\r\n   kohteessa System.Web.Compilation.BuildManager.GetVPathBuildResultWithNoAssert(HttpContext context, VirtualPath virtualPath, Boolean noBuild, Boolean allowCrossApp, Boolean allowBuildInPrecompile, Boolean throwIfNotFound, Boolean ensureIsUpToDate)\r\n   kohteessa System.Web.Compilation.BuildManager.GetVirtualPathObjectFactory(VirtualPath virtualPath, HttpContext context, Boolean allowCrossApp, Boolean throwIfNotFound)\r\n   kohteessa System.Web.Compilation.BuildManager.GetCompiledType(VirtualPath virtualPath)\r\n   kohteessa System.Web.Compilation.BuildManager.GetCompiledType(String virtualPath)\r\n   kohteessa System.Web.Mvc.BuildManagerWrapper.System.Web.Mvc.IBuildManager.GetCompiledType(String virtualPath)\r\n   kohteessa System.Web.Mvc.BuildManagerCompiledView.Render(ViewContext viewContext, TextWriter writer)\r\n   kohteessa Umbraco.Web.Mvc.ProfilingView.Render(ViewContext viewContext, TextWriter writer) tiedostossa d:\\a\\1\\s\\src\\Umbraco.Web\\Mvc\\ProfilingView.cs:rivillä 25\r\n   kohteessa System.Web.Mvc.ViewResultBase.ExecuteResult(ControllerContext context)\r\n   kohteessa System.Web.Mvc.ControllerActionInvoker.InvokeActionResult(ControllerContext controllerContext, ActionResult actionResult)\r\n   kohteessa System.Web.Mvc.ControllerActionInvoker.InvokeActionResultFilterRecursive(IList`1 filters, Int32 filterIndex, ResultExecutingContext preContext, ControllerContext controllerContext, ActionResult actionResult)\r\n   kohteessa System.Web.Mvc.ControllerActionInvoker.InvokeActionResultFilterRecursive(IList`1 filters, Int32 filterIndex, ResultExecutingContext preContext, ControllerContext controllerContext, ActionResult actionResult)\r\n   kohteessa System.Web.Mvc.ControllerActionInvoker.InvokeActionResultFilterRecursive(IList`1 filters, Int32 filterIndex, ResultExecutingContext preContext, ControllerContext controllerContext, ActionResult actionResult)\r\n   kohteessa System.Web.Mvc.ControllerActionInvoker.InvokeActionResultFilterRecursive(IList`1 filters, Int32 filterIndex, ResultExecutingContext preContext, ControllerContext controllerContext, ActionResult actionResult)\r\n   kohteessa System.Web.Mvc.ControllerActionInvoker.InvokeActionResultWithFilters(ControllerContext controllerContext, IList`1 filters, ActionResult actionResult)\r\n   kohteessa System.Web.Mvc.Async.AsyncControllerActionInvoker.<>c__DisplayClass3_6.<BeginInvokeAction>b__4()\r\n   kohteessa System.Web.Mvc.Async.AsyncControllerActionInvoker.<>c__DisplayClass3_1.<BeginInvokeAction>b__1(IAsyncResult asyncResult)\r\n   kohteessa System.Web.Mvc.Async.AsyncResultWrapper.WrappedAsyncResult`1.CallEndDelegate(IAsyncResult asyncResult)\r\n   kohteessa System.Web.Mvc.Async.AsyncResultWrapper.WrappedAsyncResultBase`1.End()\r\n   kohteessa System.Web.Mvc.Async.AsyncControllerActionInvoker.EndInvokeAction(IAsyncResult asyncResult)\r\n   kohteessa System.Web.Mvc.Controller.<>c.<BeginExecuteCore>b__152_1(IAsyncResult asyncResult, ExecuteCoreState innerState)\r\n   kohteessa System.Web.Mvc.Async.AsyncResultWrapper.WrappedAsyncVoid`1.CallEndDelegate(IAsyncResult asyncResult)\r\n   kohteessa System.Web.Mvc.Async.AsyncResultWrapper.WrappedAsyncResultBase`1.End()\r\n   kohteessa System.Web.Mvc.Controller.EndExecuteCore(IAsyncResult asyncResult)\r\n   kohteessa System.Web.Mvc.Controller.<>c.<BeginExecute>b__151_2(IAsyncResult asyncResult, Controller controller)\r\n   kohteessa System.Web.Mvc.Async.AsyncResultWrapper.WrappedAsyncVoid`1.CallEndDelegate(IAsyncResult asyncResult)\r\n   kohteessa System.Web.Mvc.Async.AsyncResultWrapper.WrappedAsyncResultBase`1.End()\r\n   kohteessa System.Web.Mvc.Controller.EndExecute(IAsyncResult asyncResult)\r\n   kohteessa System.Web.Mvc.Controller.System.Web.Mvc.Async.IAsyncController.EndExecute(IAsyncResult asyncResult)\r\n   kohteessa System.Web.Mvc.MvcHandler.<>c.<BeginProcessRequest>b__20_1(IAsyncResult asyncResult, ProcessRequestState innerState)\r\n   kohteessa System.Web.Mvc.Async.AsyncResultWrapper.WrappedAsyncVoid`1.CallEndDelegate(IAsyncResult asyncResult)\r\n   kohteessa System.Web.Mvc.Async.AsyncResultWrapper.WrappedAsyncResultBase`1.End()\r\n   kohteessa System.Web.Mvc.MvcHandler.EndProcessRequest(IAsyncResult asyncResult)\r\n   kohteessa System.Web.Mvc.MvcHandler.System.Web.IHttpAsyncHandler.EndProcessRequest(IAsyncResult result)\r\n   kohteessa System.Web.HttpApplication.CallHandlerExecutionStep.System.Web.HttpApplication.IExecutionStep.Execute()\r\n   kohteessa System.Web.HttpApplication.ExecuteStepImpl(IExecutionStep step)\r\n   kohteessa System.Web.HttpApplication.ExecuteStep(IExecutionStep step, Boolean& completedSynchronously)","SourceContext":"Umbraco.Web.UmbracoApplicationBase","ProcessId":9500,"ProcessName":"iisexpress","ThreadId":17,"AppDomainId":2,"AppDomainAppId":"LMW3SVC2ROOT","MachineName":"LAPTOP-7D4JH2DL","Log4NetLevel":"ERROR","HttpSessionId":"p55pvjv4byyo4skruetj2nb3","HttpRequestNumber":9,"HttpRequestId":"12d3f36f-e569-470f-a48a-cffc74a04604"}
{"@t":"2019-10-21T09:01:42.4918779Z","@mt":"An unhandled exception occurred","@l":"Error","@x":"System.Web.HttpCompileException (0x80004005): C:\\Users\\tanel\\source\\repos\\gnollhack-website3\\gnollhack-website\\gnollhack2\\Views\\ItemCategory.cshtml(20): error CS0103: The name 'itemClass' does not exist in the current context\r\n   kohteessa System.Web.Compilation.AssemblyBuilder.Compile()\r\n   kohteessa System.Web.Compilation.BuildProvidersCompiler.PerformBuild()\r\n   kohteessa System.Web.Compilation.BuildManager.CompileWebFile(VirtualPath virtualPath)\r\n   kohteessa System.Web.Compilation.BuildManager.GetVPathBuildResultInternal(VirtualPath virtualPath, Boolean noBuild, Boolean allowCrossApp, Boolean allowBuildInPrecompile, Boolean throwIfNotFound, Boolean ensureIsUpToDate)\r\n   kohteessa System.Web.Compilation.BuildManager.GetVPathBuildResultWithNoAssert(HttpContext context, VirtualPath virtualPath, Boolean noBuild, Boolean allowCrossApp, Boolean allowBuildInPrecompile, Boolean throwIfNotFound, Boolean ensureIsUpToDate)\r\n   kohteessa System.Web.Compilation.BuildManager.GetVirtualPathObjectFactory(VirtualPath virtualPath, HttpContext context, Boolean allowCrossApp, Boolean throwIfNotFound)\r\n   kohteessa System.Web.Compilation.BuildManager.GetCompiledType(VirtualPath virtualPath)\r\n   kohteessa System.Web.Compilation.BuildManager.GetCompiledType(String virtualPath)\r\n   kohteessa System.Web.Mvc.BuildManagerWrapper.System.Web.Mvc.IBuildManager.GetCompiledType(String virtualPath)\r\n   kohteessa System.Web.Mvc.BuildManagerCompiledView.Render(ViewContext viewContext, TextWriter writer)\r\n   kohteessa Umbraco.Web.Mvc.ProfilingView.Render(ViewContext viewContext, TextWriter writer) tiedostossa d:\\a\\1\\s\\src\\Umbraco.Web\\Mvc\\ProfilingView.cs:rivillä 25\r\n   kohteessa System.Web.Mvc.ViewResultBase.ExecuteResult(ControllerContext context)\r\n   kohteessa System.Web.Mvc.ControllerActionInvoker.InvokeActionResult(ControllerContext controllerContext, ActionResult actionResult)\r\n   kohteessa System.Web.Mvc.ControllerActionInvoker.InvokeActionResultFilterRecursive(IList`1 filters, Int32 filterIndex, ResultExecutingContext preContext, ControllerContext controllerContext, ActionResult actionResult)\r\n   kohteessa System.Web.Mvc.ControllerActionInvoker.InvokeActionResultFilterRecursive(IList`1 filters, Int32 filterIndex, ResultExecutingContext preContext, ControllerContext controllerContext, ActionResult actionResult)\r\n   kohteessa System.Web.Mvc.ControllerActionInvoker.InvokeActionResultFilterRecursive(IList`1 filters, Int32 filterIndex, ResultExecutingContext preContext, ControllerContext controllerContext, ActionResult actionResult)\r\n   kohteessa System.Web.Mvc.ControllerActionInvoker.InvokeActionResultFilterRecursive(IList`1 filters, Int32 filterIndex, ResultExecutingContext preContext, ControllerContext controllerContext, ActionResult actionResult)\r\n   kohteessa System.Web.Mvc.ControllerActionInvoker.InvokeActionResultWithFilters(ControllerContext controllerContext, IList`1 filters, ActionResult actionResult)\r\n   kohteessa System.Web.Mvc.Async.AsyncControllerActionInvoker.<>c__DisplayClass3_6.<BeginInvokeAction>b__4()\r\n   kohteessa System.Web.Mvc.Async.AsyncControllerActionInvoker.<>c__DisplayClass3_1.<BeginInvokeAction>b__1(IAsyncResult asyncResult)\r\n   kohteessa System.Web.Mvc.Async.AsyncResultWrapper.WrappedAsyncResult`1.CallEndDelegate(IAsyncResult asyncResult)\r\n   kohteessa System.Web.Mvc.Async.AsyncResultWrapper.WrappedAsyncResultBase`1.End()\r\n   kohteessa System.Web.Mvc.Async.AsyncControllerActionInvoker.EndInvokeAction(IAsyncResult asyncResult)\r\n   kohteessa System.Web.Mvc.Controller.<>c.<BeginExecuteCore>b__152_1(IAsyncResult asyncResult, ExecuteCoreState innerState)\r\n   kohteessa System.Web.Mvc.Async.AsyncResultWrapper.WrappedAsyncVoid`1.CallEndDelegate(IAsyncResult asyncResult)\r\n   kohteessa System.Web.Mvc.Async.AsyncResultWrapper.WrappedAsyncResultBase`1.End()\r\n   kohteessa System.Web.Mvc.Controller.EndExecuteCore(IAsyncResult asyncResult)\r\n   kohteessa System.Web.Mvc.Controller.<>c.<BeginExecute>b__151_2(IAsyncResult asyncResult, Controller controller)\r\n   kohteessa System.Web.Mvc.Async.AsyncResultWrapper.WrappedAsyncVoid`1.CallEndDelegate(IAsyncResult asyncResult)\r\n   kohteessa System.Web.Mvc.Async.AsyncResultWrapper.WrappedAsyncResultBase`1.End()\r\n   kohteessa System.Web.Mvc.Controller.EndExecute(IAsyncResult asyncResult)\r\n   kohteessa System.Web.Mvc.Controller.System.Web.Mvc.Async.IAsyncController.EndExecute(IAsyncResult asyncResult)\r\n   kohteessa System.Web.Mvc.MvcHandler.<>c.<BeginProcessRequest>b__20_1(IAsyncResult asyncResult, ProcessRequestState innerState)\r\n   kohteessa System.Web.Mvc.Async.AsyncResultWrapper.WrappedAsyncVoid`1.CallEndDelegate(IAsyncResult asyncResult)\r\n   kohteessa System.Web.Mvc.Async.AsyncResultWrapper.WrappedAsyncResultBase`1.End()\r\n   kohteessa System.Web.Mvc.MvcHandler.EndProcessRequest(IAsyncResult asyncResult)\r\n   kohteessa System.Web.Mvc.MvcHandler.System.Web.IHttpAsyncHandler.EndProcessRequest(IAsyncResult result)\r\n   kohteessa System.Web.HttpApplication.CallHandlerExecutionStep.System.Web.HttpApplication.IExecutionStep.Execute()\r\n   kohteessa System.Web.HttpApplication.ExecuteStepImpl(IExecutionStep step)\r\n   kohteessa System.Web.HttpApplication.ExecuteStep(IExecutionStep step, Boolean& completedSynchronously)","SourceContext":"Umbraco.Web.UmbracoApplicationBase","ProcessId":9500,"ProcessName":"iisexpress","ThreadId":40,"AppDomainId":2,"AppDomainAppId":"LMW3SVC2ROOT","MachineName":"LAPTOP-7D4JH2DL","Log4NetLevel":"ERROR","HttpSessionId":"12jwbjolrqbles02p4lp1ocj","HttpRequestNumber":10,"HttpRequestId":"e9f7636b-c0d2-4a38-8cc2-a09ddcb94f18"}
{"@t":"2019-10-21T09:06:38.0894277Z","@mt":"An unhandled exception occurred","@l":"Error","@x":"System.NullReferenceException: No property type found with alias content\r\n   kohteessa Umbraco.Web.GridTemplateExtensions.GetGridHtml(HtmlHelper html, IPublishedContent contentItem, String propertyAlias, String framework) tiedostossa d:\\a\\1\\s\\src\\Umbraco.Web\\GridTemplateExtensions.cs:rivillä 40\r\n   kohteessa Umbraco.Web.GridTemplateExtensions.GetGridHtml(HtmlHelper html, IPublishedContent contentItem, String propertyAlias) tiedostossa d:\\a\\1\\s\\src\\Umbraco.Web\\GridTemplateExtensions.cs:rivillä 31\r\n   kohteessa ASP._Page_Views_text_cshtml.Execute() tiedostossa C:\\Users\\tanel\\source\\repos\\gnollhack-website3\\gnollhack-website\\gnollhack2\\Views\\text.cshtml:rivillä 8\r\n   kohteessa System.Web.WebPages.WebPageBase.ExecutePageHierarchy()\r\n   kohteessa System.Web.Mvc.WebViewPage.ExecutePageHierarchy()\r\n   kohteessa System.Web.WebPages.WebPageBase.ExecutePageHierarchy(WebPageContext pageContext, TextWriter writer, WebPageRenderingBase startPage)\r\n   kohteessa System.Web.WebPages.WebPageBase.<>c__DisplayClass40_0.<RenderPageCore>b__0(TextWriter writer)\r\n   kohteessa System.Web.WebPages.HelperResult.WriteTo(TextWriter writer)\r\n   kohteessa System.Web.WebPages.WebPageBase.Write(HelperResult result)\r\n   kohteessa System.Web.WebPages.WebPageBase.RenderSurrounding(String partialViewName, Action`1 body)\r\n   kohteessa System.Web.WebPages.WebPageBase.PopContext()\r\n   kohteessa System.Web.WebPages.WebPageBase.ExecutePageHierarchy(WebPageContext pageContext, TextWriter writer, WebPageRenderingBase startPage)\r\n   kohteessa System.Web.WebPages.WebPageBase.<>c__DisplayClass40_0.<RenderPageCore>b__0(TextWriter writer)\r\n   kohteessa System.Web.WebPages.HelperResult.WriteTo(TextWriter writer)\r\n   kohteessa System.Web.WebPages.WebPageBase.Write(HelperResult result)\r\n   kohteessa System.Web.WebPages.WebPageBase.RenderSurrounding(String partialViewName, Action`1 body)\r\n   kohteessa System.Web.WebPages.WebPageBase.PopContext()\r\n   kohteessa System.Web.WebPages.WebPageBase.ExecutePageHierarchy(WebPageContext pageContext, TextWriter writer, WebPageRenderingBase startPage)\r\n   kohteessa System.Web.Mvc.RazorView.RenderView(ViewContext viewContext, TextWriter writer, Object instance)\r\n   kohteessa System.Web.Mvc.BuildManagerCompiledView.Render(ViewContext viewContext, TextWriter writer)\r\n   kohteessa Umbraco.Web.Mvc.ProfilingView.Render(ViewContext viewContext, TextWriter writer) tiedostossa d:\\a\\1\\s\\src\\Umbraco.Web\\Mvc\\ProfilingView.cs:rivillä 25\r\n   kohteessa System.Web.Mvc.ViewResultBase.ExecuteResult(ControllerContext context)\r\n   kohteessa System.Web.Mvc.ControllerActionInvoker.InvokeActionResult(ControllerContext controllerContext, ActionResult actionResult)\r\n   kohteessa System.Web.Mvc.ControllerActionInvoker.InvokeActionResultFilterRecursive(IList`1 filters, Int32 filterIndex, ResultExecutingContext preContext, ControllerContext controllerContext, ActionResult actionResult)\r\n   kohteessa System.Web.Mvc.ControllerActionInvoker.InvokeActionResultFilterRecursive(IList`1 filters, Int32 filterIndex, ResultExecutingContext preContext, ControllerContext controllerContext, ActionResult actionResult)\r\n   kohteessa System.Web.Mvc.ControllerActionInvoker.InvokeActionResultFilterRecursive(IList`1 filters, Int32 filterIndex, ResultExecutingContext preContext, ControllerContext controllerContext, ActionResult actionResult)\r\n   kohteessa System.Web.Mvc.ControllerActionInvoker.InvokeActionResultFilterRecursive(IList`1 filters, Int32 filterIndex, ResultExecutingContext preContext, ControllerContext controllerContext, ActionResult actionResult)\r\n   kohteessa System.Web.Mvc.ControllerActionInvoker.InvokeActionResultWithFilters(ControllerContext controllerContext, IList`1 filters, ActionResult actionResult)\r\n   kohteessa System.Web.Mvc.Async.AsyncControllerActionInvoker.<>c__DisplayClass3_6.<BeginInvokeAction>b__4()\r\n   kohteessa System.Web.Mvc.Async.AsyncControllerActionInvoker.<>c__DisplayClass3_1.<BeginInvokeAction>b__1(IAsyncResult asyncResult)\r\n   kohteessa System.Web.Mvc.Async.AsyncResultWrapper.WrappedAsyncResult`1.CallEndDelegate(IAsyncResult asyncResult)\r\n   kohteessa System.Web.Mvc.Async.AsyncResultWrapper.WrappedAsyncResultBase`1.End()\r\n   kohteessa System.Web.Mvc.Async.AsyncControllerActionInvoker.EndInvokeAction(IAsyncResult asyncResult)\r\n   kohteessa System.Web.Mvc.Controller.<>c.<BeginExecuteCore>b__152_1(IAsyncResult asyncResult, ExecuteCoreState innerState)\r\n   kohteessa System.Web.Mvc.Async.AsyncResultWrapper.WrappedAsyncVoid`1.CallEndDelegate(IAsyncResult asyncResult)\r\n   kohteessa System.Web.Mvc.Async.AsyncResultWrapper.WrappedAsyncResultBase`1.End()\r\n   kohteessa System.Web.Mvc.Controller.EndExecuteCore(IAsyncResult asyncResult)\r\n   kohteessa System.Web.Mvc.Controller.<>c.<BeginExecute>b__151_2(IAsyncResult asyncResult, Controller controller)\r\n   kohteessa System.Web.Mvc.Async.AsyncResultWrapper.WrappedAsyncVoid`1.CallEndDelegate(IAsyncResult asyncResult)\r\n   kohteessa System.Web.Mvc.Async.AsyncResultWrapper.WrappedAsyncResultBase`1.End()\r\n   kohteessa System.Web.Mvc.Controller.EndExecute(IAsyncResult asyncResult)\r\n   kohteessa System.Web.Mvc.Controller.System.Web.Mvc.Async.IAsyncController.EndExecute(IAsyncResult asyncResult)\r\n   kohteessa System.Web.Mvc.MvcHandler.<>c.<BeginProcessRequest>b__20_1(IAsyncResult asyncResult, ProcessRequestState innerState)\r\n   kohteessa System.Web.Mvc.Async.AsyncResultWrapper.WrappedAsyncVoid`1.CallEndDelegate(IAsyncResult asyncResult)\r\n   kohteessa System.Web.Mvc.Async.AsyncResultWrapper.WrappedAsyncResultBase`1.End()\r\n   kohteessa System.Web.Mvc.MvcHandler.EndProcessRequest(IAsyncResult asyncResult)\r\n   kohteessa System.Web.Mvc.MvcHandler.System.Web.IHttpAsyncHandler.EndProcessRequest(IAsyncResult result)\r\n   kohteessa System.Web.HttpApplication.CallHandlerExecutionStep.System.Web.HttpApplication.IExecutionStep.Execute()\r\n   kohteessa System.Web.HttpApplication.ExecuteStepImpl(IExecutionStep step)\r\n   kohteessa System.Web.HttpApplication.ExecuteStep(IExecutionStep step, Boolean& completedSynchronously)","SourceContext":"Umbraco.Web.UmbracoApplicationBase","ProcessId":9500,"ProcessName":"iisexpress","ThreadId":48,"AppDomainId":2,"AppDomainAppId":"LMW3SVC2ROOT","MachineName":"LAPTOP-7D4JH2DL","Log4NetLevel":"ERROR","HttpSessionId":"1lyifuh55favhoh4mvv5lmla","HttpRequestNumber":11,"HttpRequestId":"1794c01e-199c-46cf-8110-ca354441e8ba"}
{"@t":"2019-10-21T09:15:31.4614299Z","@mt":"[{EventType}] Event Id: {EventId}, State: {State}","EventType":"Information","EventId":0,"State":"User logged will be logged out due to timeout: taneli.juga@hyvanmielenpelit.fi, IP Address: ::1","SourceContext":"Umbraco.Core.Logging.OwinLogger","ProcessId":9500,"ProcessName":"iisexpress","ThreadId":76,"AppDomainId":2,"AppDomainAppId":"LMW3SVC2ROOT","MachineName":"LAPTOP-7D4JH2DL","Log4NetLevel":"INFO ","HttpRequestNumber":12,"HttpRequestId":"eaa4d6e5-a962-46fc-9d16-fe548c8950e9"}
{"@t":"2019-10-21T10:24:09.5141584Z","@mt":"[{EventType}] Event Id: {EventId}, State: {State}","EventType":"Information","EventId":0,"State":"Login attempt succeeded for username taneli.juga@hyvanmielenpelit.fi from IP address ::1","SourceContext":"Umbraco.Core.Logging.OwinLogger","ProcessId":9500,"ProcessName":"iisexpress","ThreadId":93,"AppDomainId":2,"AppDomainAppId":"LMW3SVC2ROOT","MachineName":"LAPTOP-7D4JH2DL","Log4NetLevel":"INFO ","HttpRequestNumber":13,"HttpRequestId":"3745e67d-f899-4be1-a411-5b3ebdc5bd68"}
{"@t":"2019-10-21T10:24:09.5141584Z","@mt":"[{EventType}] Event Id: {EventId}, State: {State}","EventType":"Information","EventId":0,"State":"User: taneli.juga@hyvanmielenpelit.fi logged in from IP address ::1","SourceContext":"Umbraco.Core.Logging.OwinLogger","ProcessId":9500,"ProcessName":"iisexpress","ThreadId":93,"AppDomainId":2,"AppDomainAppId":"LMW3SVC2ROOT","MachineName":"LAPTOP-7D4JH2DL","Log4NetLevel":"INFO ","HttpRequestNumber":13,"HttpRequestId":"3745e67d-f899-4be1-a411-5b3ebdc5bd68"}
{"@t":"2019-10-21T10:39:31.0707534Z","@mt":"Document {ContentName} (id={ContentId}) has been published.","ContentName":"Monsters","ContentId":1128,"SourceContext":"Umbraco.Core.Services.Implement.ContentService","ProcessId":9500,"ProcessName":"iisexpress","ThreadId":92,"AppDomainId":2,"AppDomainAppId":"LMW3SVC2ROOT","MachineName":"LAPTOP-7D4JH2DL","Log4NetLevel":"INFO ","HttpRequestNumber":14,"HttpRequestId":"32982d66-7bf6-4c0d-9675-056365ad31c1"}
{"@t":"2019-10-21T10:46:05.3748028Z","@mt":"Document {ContentName} (id={ContentId}) has been published.","ContentName":"Insect","ContentId":1129,"SourceContext":"Umbraco.Core.Services.Implement.ContentService","ProcessId":9500,"ProcessName":"iisexpress","ThreadId":69,"AppDomainId":2,"AppDomainAppId":"LMW3SVC2ROOT","MachineName":"LAPTOP-7D4JH2DL","Log4NetLevel":"INFO ","HttpRequestNumber":15,"HttpRequestId":"b16aa135-ba6a-4bd3-9399-eee73de6971a"}
{"@t":"2019-10-21T10:46:27.4701088Z","@mt":"Document {ContentName} (id={ContentId}) has been published.","ContentName":"Soldier ant","ContentId":1130,"SourceContext":"Umbraco.Core.Services.Implement.ContentService","ProcessId":9500,"ProcessName":"iisexpress","ThreadId":32,"AppDomainId":2,"AppDomainAppId":"LMW3SVC2ROOT","MachineName":"LAPTOP-7D4JH2DL","Log4NetLevel":"INFO ","HttpRequestNumber":16,"HttpRequestId":"6311d78d-6008-4246-bccf-c72729931ad9"}
{"@t":"2019-10-21T10:54:46.9879027Z","@mt":"Document {ContentName} (id={ContentId}) has been published.","ContentName":"Blob","ContentId":0,"SourceContext":"Umbraco.Core.Services.Implement.ContentService","ProcessId":9500,"ProcessName":"iisexpress","ThreadId":66,"AppDomainId":2,"AppDomainAppId":"LMW3SVC2ROOT","MachineName":"LAPTOP-7D4JH2DL","Log4NetLevel":"INFO ","HttpRequestNumber":17,"HttpRequestId":"96cf6103-b49f-4748-af0c-afec2788fed2"}
{"@t":"2019-10-21T10:56:06.0471835Z","@mt":"Document {ContentName} (id={ContentId}) has been published.","ContentName":"Acid blob","ContentId":0,"SourceContext":"Umbraco.Core.Services.Implement.ContentService","ProcessId":9500,"ProcessName":"iisexpress","ThreadId":72,"AppDomainId":2,"AppDomainAppId":"LMW3SVC2ROOT","MachineName":"LAPTOP-7D4JH2DL","Log4NetLevel":"INFO ","HttpRequestNumber":18,"HttpRequestId":"bfab1b4f-d8de-47f5-91d5-94c0137eca92"}
{"@t":"2019-10-21T10:56:20.5318421Z","@mt":"Document {ContentName} (id={ContentId}) has been published.","ContentName":"Acid blob","ContentId":1187,"SourceContext":"Umbraco.Core.Services.Implement.ContentService","ProcessId":9500,"ProcessName":"iisexpress","ThreadId":69,"AppDomainId":2,"AppDomainAppId":"LMW3SVC2ROOT","MachineName":"LAPTOP-7D4JH2DL","Log4NetLevel":"INFO ","HttpRequestNumber":19,"HttpRequestId":"14259071-56a9-4177-bf42-b2910d7ef90a"}
{"@t":"2019-10-21T10:57:25.8287061Z","@mt":"Document {ContentName} (id={ContentId}) has been published.","ContentName":"Acid blob","ContentId":1187,"SourceContext":"Umbraco.Core.Services.Implement.ContentService","ProcessId":9500,"ProcessName":"iisexpress","ThreadId":80,"AppDomainId":2,"AppDomainAppId":"LMW3SVC2ROOT","MachineName":"LAPTOP-7D4JH2DL","Log4NetLevel":"INFO ","HttpRequestNumber":20,"HttpRequestId":"045b458d-77f0-4bba-8d64-3394f0d3f62d"}
{"@t":"2019-10-21T10:59:54.0997503Z","@mt":"Document {ContentName} (id={ContentId}) has been published.","ContentName":"Quivering blob","ContentId":0,"SourceContext":"Umbraco.Core.Services.Implement.ContentService","ProcessId":9500,"ProcessName":"iisexpress","ThreadId":66,"AppDomainId":2,"AppDomainAppId":"LMW3SVC2ROOT","MachineName":"LAPTOP-7D4JH2DL","Log4NetLevel":"INFO ","HttpRequestNumber":21,"HttpRequestId":"01826244-9cf0-4eb1-8598-50c55b8d9ae0"}
{"@t":"2019-10-21T11:10:34.4092996Z","@mt":"[{EventType}] Event Id: {EventId}, State: {State}","EventType":"Information","EventId":0,"State":"User logged will be logged out due to timeout: taneli.juga@hyvanmielenpelit.fi, IP Address: ::1","SourceContext":"Umbraco.Core.Logging.OwinLogger","ProcessId":9500,"ProcessName":"iisexpress","ThreadId":45,"AppDomainId":2,"AppDomainAppId":"LMW3SVC2ROOT","MachineName":"LAPTOP-7D4JH2DL","Log4NetLevel":"INFO ","HttpRequestNumber":22,"HttpRequestId":"d1a1ce1f-e781-4209-8690-0eac477c5f6b"}
{"@t":"2019-10-21T11:10:40.4015462Z","@mt":"[{EventType}] Event Id: {EventId}, State: {State}","EventType":"Information","EventId":0,"State":"User logged will be logged out due to timeout: taneli.juga@hyvanmielenpelit.fi, IP Address: ::1","SourceContext":"Umbraco.Core.Logging.OwinLogger","ProcessId":9500,"ProcessName":"iisexpress","ThreadId":38,"AppDomainId":2,"AppDomainAppId":"LMW3SVC2ROOT","MachineName":"LAPTOP-7D4JH2DL","Log4NetLevel":"INFO ","HttpRequestNumber":23,"HttpRequestId":"04ed5f2c-5a15-48f3-81bf-d8fd850a5b3f"}
{"@t":"2019-10-21T11:15:55.5633918Z","@mt":"[{EventType}] Event Id: {EventId}, State: {State}","EventType":"Information","EventId":0,"State":"Login attempt succeeded for username taneli.juga@hyvanmielenpelit.fi from IP address ::1","SourceContext":"Umbraco.Core.Logging.OwinLogger","ProcessId":9500,"ProcessName":"iisexpress","ThreadId":26,"AppDomainId":2,"AppDomainAppId":"LMW3SVC2ROOT","MachineName":"LAPTOP-7D4JH2DL","Log4NetLevel":"INFO ","HttpRequestNumber":24,"HttpRequestId":"b26723dc-dfc0-46a4-8a77-607609a0755a"}
{"@t":"2019-10-21T11:15:55.5633918Z","@mt":"[{EventType}] Event Id: {EventId}, State: {State}","EventType":"Information","EventId":0,"State":"User: taneli.juga@hyvanmielenpelit.fi logged in from IP address ::1","SourceContext":"Umbraco.Core.Logging.OwinLogger","ProcessId":9500,"ProcessName":"iisexpress","ThreadId":26,"AppDomainId":2,"AppDomainAppId":"LMW3SVC2ROOT","MachineName":"LAPTOP-7D4JH2DL","Log4NetLevel":"INFO ","HttpRequestNumber":24,"HttpRequestId":"b26723dc-dfc0-46a4-8a77-607609a0755a"}
{"@t":"2019-10-21T11:15:56.1853794Z","@mt":"[{EventType}] Event Id: {EventId}, State: {State}","EventType":"Information","EventId":0,"State":"Login attempt succeeded for username taneli.juga@hyvanmielenpelit.fi from IP address ::1","SourceContext":"Umbraco.Core.Logging.OwinLogger","ProcessId":9500,"ProcessName":"iisexpress","ThreadId":22,"AppDomainId":2,"AppDomainAppId":"LMW3SVC2ROOT","MachineName":"LAPTOP-7D4JH2DL","Log4NetLevel":"INFO ","HttpRequestNumber":25,"HttpRequestId":"57990166-173c-4758-8ce3-5f11e15d0514"}
{"@t":"2019-10-21T11:15:56.1853794Z","@mt":"[{EventType}] Event Id: {EventId}, State: {State}","EventType":"Information","EventId":0,"State":"User: taneli.juga@hyvanmielenpelit.fi logged in from IP address ::1","SourceContext":"Umbraco.Core.Logging.OwinLogger","ProcessId":9500,"ProcessName":"iisexpress","ThreadId":22,"AppDomainId":2,"AppDomainAppId":"LMW3SVC2ROOT","MachineName":"LAPTOP-7D4JH2DL","Log4NetLevel":"INFO ","HttpRequestNumber":25,"HttpRequestId":"57990166-173c-4758-8ce3-5f11e15d0514"}
{"@t":"2019-10-21T11:15:59.4315339Z","@mt":"[{EventType}] Event Id: {EventId}, State: {State}","EventType":"Information","EventId":0,"State":"Login attempt succeeded for username taneli.juga@hyvanmielenpelit.fi from IP address ::1","SourceContext":"Umbraco.Core.Logging.OwinLogger","ProcessId":9500,"ProcessName":"iisexpress","ThreadId":22,"AppDomainId":2,"AppDomainAppId":"LMW3SVC2ROOT","MachineName":"LAPTOP-7D4JH2DL","Log4NetLevel":"INFO ","HttpRequestNumber":26,"HttpRequestId":"0ef16558-8e9c-4d64-8b54-273e2b58685d"}
{"@t":"2019-10-21T11:15:59.4315339Z","@mt":"[{EventType}] Event Id: {EventId}, State: {State}","EventType":"Information","EventId":0,"State":"User: taneli.juga@hyvanmielenpelit.fi logged in from IP address ::1","SourceContext":"Umbraco.Core.Logging.OwinLogger","ProcessId":9500,"ProcessName":"iisexpress","ThreadId":22,"AppDomainId":2,"AppDomainAppId":"LMW3SVC2ROOT","MachineName":"LAPTOP-7D4JH2DL","Log4NetLevel":"INFO ","HttpRequestNumber":26,"HttpRequestId":"0ef16558-8e9c-4d64-8b54-273e2b58685d"}
{"@t":"2019-10-21T11:39:48.5792650Z","@mt":"Document {ContentName} (id={ContentId}) has been published.","ContentName":"Spells","ContentId":1086,"SourceContext":"Umbraco.Core.Services.Implement.ContentService","ProcessId":9500,"ProcessName":"iisexpress","ThreadId":5,"AppDomainId":2,"AppDomainAppId":"LMW3SVC2ROOT","MachineName":"LAPTOP-7D4JH2DL","Log4NetLevel":"INFO ","HttpRequestNumber":27,"HttpRequestId":"4dcd58c5-ff93-4a26-b409-3974e28ea256"}
